zorg_grove-0.0.4.dist-info/RECORD
zorg_grove-0.0.4.dist-info/top_level.txt
zorg_grove-0.0.4.dist-info/metadata.json
zorg_grove-0.0.4.dist-info/zip-safe
zorg_grove-0.0.4.dist-info/METADATA
zorg_grove-0.0.4.dist-info/DESCRIPTION.rst
zorg_grove-0.0.4.dist-info/WHEEL
tests/mock_device.py
tests/test_devices.py
tests/__init__.py
tests/test_lcd.py
tests/smoke_tests/test_commands.py
tests/smoke_tests/__init__.py
zorg_grove/lcd.py
zorg_grove/rotary_angle_sensor.py
zorg_grove/servo.py
zorg_grove/temperature_sensor.py
zorg_grove/__init__.py
zorg_grove/microphone.py
